setup.py
dread/__init__.py
dread/base.py
dread/json.py
dread.egg-info/PKG-INFO
dread.egg-info/SOURCES.txt
dread.egg-info/dependency_links.txt
dread.egg-info/requires.txt
dread.egg-info/top_level.txt